supercanvas/__init__.py
supercanvas/supercanvas.py
supercanvas-0.6.6.dist-info/METADATA
supercanvas-0.6.6.dist-info/WHEEL
supercanvas-0.6.6.dist-info/top_level.txt
supercanvas-0.6.6.dist-info/RECORD
