Metadata-Version: 2.1
Name: supercanvas
Version: 0.6.6
Summary: tkinter simplified (and augmented) canvas
Home-page: https://twitter.com/david_cobac
Author: David COBAC
Author-email: david.cobac@gmail.com
License: CC-BY-NC-SA
Keywords: tkinter,canvas,cartesian,repère
Platform: UNKNOWN
Requires-Python: >3.2
